py4j/__init__.py
py4j/clientserver.py
py4j/compat.py
py4j/finalizer.py
py4j/java_collections.py
py4j/java_gateway.py
py4j/protocol.py
py4j/signals.py
py4j/version.py
py4j/tests/__init__.py
py4j/tests/benchmark1.py
py4j/tests/byte_string_test.py
py4j/tests/client_server_test.py
py4j/tests/finalizer_test.py
py4j/tests/instrumented.py
py4j/tests/java_array_test.py
py4j/tests/java_callback_test.py
py4j/tests/java_dir_test.py
py4j/tests/java_gateway_test.py
py4j/tests/java_help_test.py
py4j/tests/java_list_test.py
py4j/tests/java_map_test.py
py4j/tests/java_set_test.py
py4j/tests/java_tls_test.py
py4j/tests/memory_leak_test.py
py4j/tests/multithreadtest.py
py4j/tests/py4j_callback_example.py
py4j/tests/py4j_callback_example2.py
py4j/tests/py4j_callback_listener_example.py
py4j/tests/py4j_callback_recursive_example.py
py4j/tests/py4j_example.py
py4j/tests/py4j_signals_test.py
py4j/tests/signals_test.py
py4j-0.10.9.6.data/data/share/py4j/py4j0.10.9.6.jar
py4j-0.10.9.6.dist-info/LICENSE.txt
py4j-0.10.9.6.dist-info/METADATA
py4j-0.10.9.6.dist-info/WHEEL
py4j-0.10.9.6.dist-info/top_level.txt
py4j-0.10.9.6.dist-info/RECORD
